wicked_print/__init__.py
wicked_print/wicked_print.py
wicked_print-0.2.0.dist-info/licenses/LICENSE
wicked_print-0.2.0.dist-info/METADATA
wicked_print-0.2.0.dist-info/WHEEL
wicked_print-0.2.0.dist-info/entry_points.txt
wicked_print-0.2.0.dist-info/top_level.txt
wicked_print-0.2.0.dist-info/RECORD
