Metadata-Version: 2.4
Name: wicked_print
Version: 0.2.0
Summary: Tiny utility that prints colorful strings one character at a time.
Author: Zhaolun Zou
License: MIT
Project-URL: Homepage, https://github.com/zergzzlun/wicked_print
Project-URL: Issues, https://github.com/zergzzlun/wicked_print/issues
Keywords: print,terminal,typing,cli
Classifier: Programming Language :: Python :: 3
Classifier: Operating System :: OS Independent
Requires-Python: >=3.7
License-File: LICENSE
Dynamic: license-file
